neuroprompt/__init__.py
neuroprompt/compressor.py
neuroprompt-0.1.3.dist-info/LICENSE
neuroprompt-0.1.3.dist-info/METADATA
neuroprompt-0.1.3.dist-info/WHEEL
neuroprompt-0.1.3.dist-info/top_level.txt
neuroprompt-0.1.3.dist-info/RECORD
