Metadata-Version: 2.1
Name: neuroprompt
Version: 0.1.3
Summary: A smart prompt compression and optimization tool for LLMs
Author-email: Tejas Chopra <chopratejas@gmail.com>
Classifier: Programming Language :: Python :: 3
Classifier: License :: OSI Approved :: MIT License
Classifier: Operating System :: OS Independent
Requires-Python: >=3.8
License-File: LICENSE
Requires-Dist: openai>=1.0.0
Requires-Dist: llmlingua>=0.1.0
Requires-Dist: tiktoken>=0.5.0
Requires-Dist: nltk>=3.8.0
Provides-Extra: eval
Requires-Dist: torch>=2.0.0; extra == "eval"
Requires-Dist: numpy>=1.24.0; extra == "eval"
Requires-Dist: rouge-score>=0.1.2; extra == "eval"
Requires-Dist: transformers>=4.0.0; extra == "eval"
Requires-Dist: scikit-learn>=1.0.0; extra == "eval"
